webhook/__init__.py
webhook/myfunctions.py
hookify-1.1.4.dist-info/METADATA
hookify-1.1.4.dist-info/WHEEL
hookify-1.1.4.dist-info/top_level.txt
hookify-1.1.4.dist-info/RECORD
