Metadata-Version: 2.1
Name: hookify
Version: 1.1.4
Summary: A modern library which allows you to efficiently and quickly send Discord webhooks.
Author: Discord >> @mcananas
